message_queue/__init__.py
message_queue/logger.py
message_queue/message.py
message_queue/publisher.py
message_queue/subscriber.py
message_queue/adapters/__init__.py
message_queue/adapters/amqp_adapter.py
message_queue/adapters/base_adapter.py
message_queue-0.3.3.dist-info/METADATA
message_queue-0.3.3.dist-info/WHEEL
message_queue-0.3.3.dist-info/top_level.txt
message_queue-0.3.3.dist-info/RECORD
