Metadata-Version: 2.1
Name: message-queue
Version: 0.3.3
Summary: Message Queue
Home-page: https://github.com/ingresse/message-queue-python
Author: Ingresse
Author-email: vitor.leal@ingresse.com
License: BSD
Download-URL: https://github.com/ingresse/message-queue-python/tarball/%r
Keywords: message queue rabbit amqp pub/sub
Platform: UNKNOWN
Requires-Dist: pika (==0.12.0)
